fstflowchat/__init__.py
fstflowchat/example.py
fstflowchat/quiz.dot
fstflowchat-0.0.7.dist-info/LICENSE
fstflowchat-0.0.7.dist-info/METADATA
fstflowchat-0.0.7.dist-info/WHEEL
fstflowchat-0.0.7.dist-info/entry_points.txt
fstflowchat-0.0.7.dist-info/top_level.txt
fstflowchat-0.0.7.dist-info/RECORD
