Metadata-Version: 2.1
Name: fstflowchat
Version: 0.0.7
Summary: a small, pedagogical, fst-based dialog toolkit.
Home-page: https://fstflowchat.readthedocs.io/en/latest/
Author: Abe Kazemzadeh
Project-URL: Bug Reports, https://github.com/abecode/fstflowchat/issues
Project-URL: Funding, https://donate.pypi.org
Project-URL: Say Thanks!, http://saythanks.io/to/example
Project-URL: Source, https://github.com/abecode/fstflowchat/issues
Keywords: dialog,dialogue,chat,finite state transducer,dialog agent,dialog system
Classifier: Development Status :: 3 - Alpha
Classifier: Intended Audience :: Developers
Classifier: License :: OSI Approved :: MIT License
Classifier: Natural Language :: English
Classifier: Topic :: Text Processing :: Linguistic
Classifier: Programming Language :: Python :: 3
Classifier: Programming Language :: Python :: 3.7
Classifier: Programming Language :: Python :: 3.8
Classifier: Programming Language :: Python :: 3.9
Classifier: Programming Language :: Python :: 3.10
Classifier: Programming Language :: Python :: 3 :: Only
Requires-Python: >=3.7, <4
License-File: LICENSE
Requires-Dist: pygraphviz
Requires-Dist: rich
